{"guides_photos_baby-小宝百天.md":"D5Isz2PG","guides_privacy_intro.md":"b9XOHbWJ","guides_tools_format_json.md":"D7G5U3qH","guides_tools_encode_url.md":"C9lSqf2q","guides_photos_baby.md":"DkgCcFxo","index.md":"DvbQc55b","guides_notes_docx_welcome.md":"gckDjB8N","guides_photos_baby-小宝出世.md":"C3_1ccz_","guides_tools_convert_image2base64.md":"pixf-PuQ","guides_photos_guanli-小宝出世.md":"Yv6yVbEz","guides_tools_format_xml.md":"DkdXnklr","guides_privacy_resume.md":"Du-ifCnB","guides_notes_docx_build.md":"DNX9CtrH","guides_photos_guanli-小宝百天.md":"BTWWOQ2Q","guides_photos_guanli.md":"C49hOmlN","guides_privacy_photos.md":"s4pomH6_","guides_tools_convert_rgb2hex.md":"BuxX2APk","guides_tools_encode_base64.md":"BQV5WbuD","guides_tools_encrypt_md5.md":"dL2Ok2gb","guides_tools_encrypt_sha.md":"BliEpG-a","guides_tools_builder_qrcode.md":"BQT6mWQb"}
